{
    "system_id": 33765, 
    "permalink": "http://collections.acmi.net.au/objects/33765", 
    "record_type": "Title", 
    "acmi_identifier": "016410", 
    "title": "Lumaaq: an Eskimo legend [French version] = Lumaaq: une legende esquimo", 
    "other_title": [
        ""
    ], 
    "other_title_type": [
        ""
    ], 
    "place_of_production": [
        "Canada"
    ], 
    "creation_date": [
        "1975"
    ], 
    "creator_contributor_role": [
        "National Film Board of Canada, production company", 
        "Pierre Moretti, producer", 
        "Co Hoedeman, director"
    ], 
    "colour": [
        "Black and White"
    ], 
    "sound_audio": [
        "Sound"
    ], 
    "language_keywords": [
        ""
    ], 
    "other_languages": [
        ""
    ], 
    "other_language_type": [
        ""
    ], 
    "other_language_notes": [
        ""
    ], 
    "length": [
        "00:07:55"
    ], 
    "audience_classification": [
        ""
    ], 
    "viewing_guidelines": [
        ""
    ], 
    "form": [
        "Short films", 
        "Short films/Short films - Canada"
    ], 
    "genre": [
        "Adaptations", 
        "Animation", 
        "Animation/Animated films - Canada"
    ], 
    "subject_group": [
        "Literature/Legends - Film and video adaptations", 
        "Anthropology, Ethnology, Exploration & Travel/Eskimos - Legends", 
        "Anthropology, Ethnology, Exploration & Travel/Inuit - Canada", 
        "Anthropology, Ethnology, Exploration & Travel/Indigenous peoples - Canada", 
        "Literature/Eskimos - Legends", 
        "History/Eskimos - Legends", 
        "Economics, Philosophy, Politics, Religion & Sociology/Cultural relativism"
    ], 
    "abstract": [
        ""
    ], 
    "description": [
        "Lumaaq tells the story of a legend widely believed by the Povungnituk Innuit. The artist's drawings are transferred to paper, cut out and animated under the camera. The result is Innuit prints in action. Dialogue, music and artwork make this film a total cultural transplant. Sound film without commentary."
    ], 
    "member_object": [
        ""
    ], 
    "part_of_compliation_title_or_vod_package": [
        ""
    ], 
    "related_objects": [
        "Title; 308127; Lumaaq: an Eskimo legend [English version]; Active; 1975"
    ], 
    "object_relationship": [
        "Related Title"
    ], 
    "related_object_notes": [
        ""
    ], 
    "active_carriers_public_types_and_formats_only": [
        "16mm film; Access Print (Section 1)"
    ]
}