{
    "system_id": 151209, 
    "permalink": "http://collections.acmi.net.au/objects/151209", 
    "record_type": "Title", 
    "acmi_identifier": "B2001563", 
    "title": "Catalyst: Fire Storm", 
    "other_title": [
        ""
    ], 
    "other_title_type": [
        ""
    ], 
    "place_of_production": [
        "Australia"
    ], 
    "creation_date": [
        "2003"
    ], 
    "creator_contributor_role": [
        "Australian Broadcasting Corporation, production company", 
        "Stefan Moore, executive producer", 
        "Ian Cuming, producer", 
        "Andrew Holland, producer", 
        "Karina Kelly, narrator"
    ], 
    "colour": [
        "Colour"
    ], 
    "sound_audio": [
        "Sound"
    ], 
    "language_keywords": [
        "English"
    ], 
    "other_languages": [
        ""
    ], 
    "other_language_type": [
        ""
    ], 
    "other_language_notes": [
        ""
    ], 
    "length": [
        "00:26:58"
    ], 
    "audience_classification": [
        "Mediatheque - all ages (ACMI classified)"
    ], 
    "viewing_guidelines": [
        ""
    ], 
    "form": [
        "Television", 
        "Television/Television programs", 
        "Television/Television programs/Television programs - Australia"
    ], 
    "genre": [
        "Educational & Instructional", 
        "Educational & Instructional/Educational films"
    ], 
    "subject_group": [
        "Climate, Environment, Natural Resources & Disasters/Wildfires", 
        "Mathematics, Science & Technology/Science", 
        "Climate, Environment, Natural Resources & Disasters/Wildfires", 
        "Climate, Environment, Natural Resources & Disasters/Wildfires - Australia"
    ], 
    "abstract": [
        "A 'Catalyst' special report on the Canberra bushfires of 2003."
    ], 
    "description": [
        "A scientific investigation into the causes of the catastrophic Canberra bushfires of January 2003 where 474 homes were destroyed and four lives lost. Includes interviews with residents, scientists, environmentalists and fire-fighters. Episode from the ABC TV series 'Catalyst' presented and narrated by Karina Kelly."
    ], 
    "member_object": [
        ""
    ], 
    "part_of_compliation_title_or_vod_package": [
        "VoD Program; B2002460; Staff Picks; Active"
    ], 
    "related_objects": [
        "Title; B2001555; After the Fires; Active; 2003"
    ], 
    "object_relationship": [
        "Related Title"
    ], 
    "related_object_notes": [
        ""
    ], 
    "active_carriers_public_types_and_formats_only": [
        "Digital Betacam [PAL]; Master", 
        "Mediatheque VoD Digital Access Copy"
    ]
}