{
    "system_id": 31999, 
    "permalink": "http://collections.acmi.net.au/objects/31999", 
    "record_type": "Title", 
    "acmi_identifier": "014111", 
    "title": "Living tomorrow. No. 096", 
    "other_title": [
        ""
    ], 
    "other_title_type": [
        ""
    ], 
    "place_of_production": [
        "United Kingdom"
    ], 
    "creation_date": [
        "1972"
    ], 
    "creator_contributor_role": [
        "Centre of Information, production company"
    ], 
    "colour": [
        "Black and White"
    ], 
    "sound_audio": [
        "Sound"
    ], 
    "language_keywords": [
        "English"
    ], 
    "other_languages": [
        ""
    ], 
    "other_language_type": [
        ""
    ], 
    "other_language_notes": [
        ""
    ], 
    "length": [
        "00:13:03"
    ], 
    "audience_classification": [
        ""
    ], 
    "viewing_guidelines": [
        ""
    ], 
    "form": [
        "Short films", 
        "Short films/Short films - Great Britain"
    ], 
    "genre": [
        "Archival, Cinemagazines & Newsreels", 
        "Archival, Cinemagazines & Newsreels/Archival materials", 
        "Documentary", 
        "Archival, Cinemagazines & Newsreels/Cinemagazines", 
        "Documentary/Documentary films - Great Britain"
    ], 
    "subject_group": [
        "Animals & Wildlife/Insect pests - Biological control", 
        "Food, Health, Lifestyle, Medicine, Psychology & Safety/Surgery", 
        "Food, Health, Lifestyle, Medicine, Psychology & Safety/Patient care", 
        "Mathematics, Science & Technology/Magnetism", 
        "Mathematics, Science & Technology/Technological innovations"
    ], 
    "abstract": [
        ""
    ], 
    "description": [
        "Cinemagazine items: Biological control of garden pests (using other insects); control of magnetism using a combination of electro and permanent (ie conventional) magnets; machine peeling of onions - a particularly delicate process; electronic monitoring and computer diagnosis of vital signs during surgery."
    ], 
    "member_object": [
        ""
    ], 
    "part_of_compliation_title_or_vod_package": [
        ""
    ], 
    "related_objects": [
        ""
    ], 
    "object_relationship": [
        ""
    ], 
    "related_object_notes": [
        ""
    ], 
    "active_carriers_public_types_and_formats_only": [
        "16mm film; Access Print (Section 1)"
    ]
}