{
    "system_id": 38831, 
    "permalink": "http://collections.acmi.net.au/objects/38831", 
    "record_type": "Title", 
    "acmi_identifier": "304103", 
    "title": "Tit for tat [Censored version]", 
    "other_title": [
        ""
    ], 
    "other_title_type": [
        ""
    ], 
    "place_of_production": [
        "Australia"
    ], 
    "creation_date": [
        "1993"
    ], 
    "creator_contributor_role": [
        "Film Australia, distributor", 
        "Film Australia, production company", 
        "Mayfan, production company", 
        "Graeme Isaac, producer"
    ], 
    "colour": [
        "Colour"
    ], 
    "sound_audio": [
        "Sound"
    ], 
    "language_keywords": [
        "English"
    ], 
    "other_languages": [
        ""
    ], 
    "other_language_type": [
        ""
    ], 
    "other_language_notes": [
        ""
    ], 
    "length": [
        "00:51:00"
    ], 
    "audience_classification": [
        ""
    ], 
    "viewing_guidelines": [
        ""
    ], 
    "form": [
        ""
    ], 
    "genre": [
        "Documentary", 
        "Documentary/Documentary films - Australia"
    ], 
    "subject_group": [
        "Food, Health, Lifestyle, Medicine, Psychology & Safety/Tattooing", 
        "Crafts & Visual Arts/Tattooing"
    ], 
    "abstract": [
        ""
    ], 
    "description": [
        "Examines the world of tattoos and the surrounding culture of bikers and rebels as the filmmaker travels with Baldy, a biker and photo-journalist, to the Sandhurst Rally for the yearly Tattoo Exhibition and judging. There they meet AJ, the most tattooed man in Australia and a renowned tattoo artist himself. WARNING - SOME SCENES IN THIS PROGRAMME MAY OFFEND SOME VIEWERS."
    ], 
    "member_object": [
        ""
    ], 
    "part_of_compliation_title_or_vod_package": [
        ""
    ], 
    "related_objects": [
        ""
    ], 
    "object_relationship": [
        ""
    ], 
    "related_object_notes": [
        ""
    ], 
    "active_carriers_public_types_and_formats_only": [
        "VHS; Access Print (Section 1)", 
        "VHS; Access Print (Section 1)", 
        "VHS; Access Print (Section 1)"
    ]
}