{
    "system_id": 22357, 
    "permalink": "http://collections.acmi.net.au/objects/22357", 
    "record_type": "Title", 
    "acmi_identifier": "002807", 
    "title": "Forward communications", 
    "other_title": [
        ""
    ], 
    "other_title_type": [
        ""
    ], 
    "place_of_production": [
        "Australia"
    ], 
    "creation_date": [
        "1949"
    ], 
    "creator_contributor_role": [
        "Australian National Film Board, production company", 
        "Bern Gandy, director"
    ], 
    "colour": [
        "Black and White"
    ], 
    "sound_audio": [
        "Sound"
    ], 
    "language_keywords": [
        "English"
    ], 
    "other_languages": [
        ""
    ], 
    "other_language_type": [
        ""
    ], 
    "other_language_notes": [
        ""
    ], 
    "length": [
        "00:10:45"
    ], 
    "audience_classification": [
        ""
    ], 
    "viewing_guidelines": [
        ""
    ], 
    "form": [
        "Short films", 
        "Short films/Short films - Australia"
    ], 
    "genre": [
        "Documentary", 
        "Documentary/Documentary films - Australia"
    ], 
    "subject_group": [
        "Communications, Infrastructure, & Transport/Telecommunication systems - History", 
        "Communications, Infrastructure, & Transport/Telecommunication - Australia", 
        "Communications, Infrastructure, & Transport/Communication", 
        "Communications, Infrastructure, & Transport/Telephone - History", 
        "History/Australia - History", 
        "Economics, Philosophy, Politics, Religion & Sociology/Communication - Social aspects"
    ], 
    "abstract": [
        ""
    ], 
    "description": [
        "Stresses that Australia's vast distances make an efficient system of communication most essential. Shows how the Post Office is maintaining our present communications system at a high level of efficiency and also how the heavy post-war demand for new telephones and exchanges is being met."
    ], 
    "member_object": [
        ""
    ], 
    "part_of_compliation_title_or_vod_package": [
        ""
    ], 
    "related_objects": [
        ""
    ], 
    "object_relationship": [
        ""
    ], 
    "related_object_notes": [
        ""
    ], 
    "active_carriers_public_types_and_formats_only": [
        "16mm film; Preservation Print (Section 5)", 
        "16mm film; Access Print (Section 1)", 
        "16mm film; Limited Access Print (Section 2)"
    ]
}