{
    "system_id": 57196, 
    "permalink": "http://collections.acmi.net.au/objects/57196", 
    "record_type": "Title", 
    "acmi_identifier": "508937", 
    "title": "Show me English: the appointment [episode 1]", 
    "other_title": [
        ""
    ], 
    "other_title_type": [
        ""
    ], 
    "place_of_production": [
        "Australia"
    ], 
    "creation_date": [
        "1986"
    ], 
    "creator_contributor_role": [
        "Victoria. Ministry of Education, production company", 
        "David Ferris, co-producer", 
        "Trevor Lunn, co-producer", 
        "Graeme Rowland, director"
    ], 
    "colour": [
        "Colour"
    ], 
    "sound_audio": [
        "Sound"
    ], 
    "language_keywords": [
        "English"
    ], 
    "other_languages": [
        ""
    ], 
    "other_language_type": [
        ""
    ], 
    "other_language_notes": [
        ""
    ], 
    "length": [
        "00:22:00"
    ], 
    "audience_classification": [
        ""
    ], 
    "viewing_guidelines": [
        ""
    ], 
    "form": [
        "Short films", 
        "Short films/Short films - Australia"
    ], 
    "genre": [
        ""
    ], 
    "subject_group": [
        "Literature/English language", 
        "Education, Instruction, Teaching & Schools/English language", 
        "Education, Instruction, Teaching & Schools/Tutors and tutoring", 
        "People/Immigrants", 
        "Economics, Philosophy, Politics, Religion & Sociology/Communication - Social aspects", 
        "Economics, Philosophy, Politics, Religion & Sociology/Immigrants"
    ], 
    "abstract": [
        ""
    ], 
    "description": [
        "A series of programmes which aim to help adult migrants communicate in everyday situations. Tina makes arrangements to visit her son's teacher to discuss his progress. Home tutor program by the Adult Migrant Information Service."
    ], 
    "member_object": [
        ""
    ], 
    "part_of_compliation_title_or_vod_package": [
        ""
    ], 
    "related_objects": [
        ""
    ], 
    "object_relationship": [
        ""
    ], 
    "related_object_notes": [
        ""
    ], 
    "active_carriers_public_types_and_formats_only": [
        "VHS; Access Print (Section 1)"
    ]
}