{
    "system_id": 48637, 
    "permalink": "http://collections.acmi.net.au/objects/48637", 
    "record_type": "Title", 
    "acmi_identifier": "314386", 
    "title": "Pelican Island", 
    "other_title": [
        ""
    ], 
    "other_title_type": [
        ""
    ], 
    "place_of_production": [
        "United States"
    ], 
    "creation_date": [
        "1930"
    ], 
    "creator_contributor_role": [
        "Burlingham Adventures, production company"
    ], 
    "colour": [
        "Tinted"
    ], 
    "sound_audio": [
        "Silent"
    ], 
    "language_keywords": [
        "English"
    ], 
    "other_languages": [
        ""
    ], 
    "other_language_type": [
        ""
    ], 
    "other_language_notes": [
        ""
    ], 
    "length": [
        "00:08:12"
    ], 
    "audience_classification": [
        ""
    ], 
    "viewing_guidelines": [
        ""
    ], 
    "form": [
        "Silent films", 
        "Short films", 
        "Short films/Short films - United States"
    ], 
    "genre": [
        ""
    ], 
    "subject_group": [
        "Animals & Wildlife/Pelicans", 
        "Animals & Wildlife/Animals", 
        "Animals & Wildlife/Animal behavior", 
        "Anthropology, Ethnology, Exploration & Travel/Florida", 
        "Places/Florida"
    ], 
    "abstract": [
        ""
    ], 
    "description": [
        "Down south in Florida where Ponde De Leon ages ago sought the spring of eternal youth, there is a queer island inhabited by pelicans. Burlington studies the map to see how the pelican get there."
    ], 
    "member_object": [
        ""
    ], 
    "part_of_compliation_title_or_vod_package": [
        ""
    ], 
    "related_objects": [
        ""
    ], 
    "object_relationship": [
        ""
    ], 
    "related_object_notes": [
        ""
    ], 
    "active_carriers_public_types_and_formats_only": [
        "16mm film; Access Print (Section 1)"
    ]
}