{
    "system_id": 37538, 
    "permalink": "http://collections.acmi.net.au/objects/37538", 
    "record_type": "Title", 
    "acmi_identifier": "302772", 
    "title": "Only One Atmosphere", 
    "other_title": [
        ""
    ], 
    "other_title_type": [
        ""
    ], 
    "place_of_production": [
        "Australia"
    ], 
    "creation_date": [
        "1990"
    ], 
    "creator_contributor_role": [
        "Film Australia, distributor", 
        "WGBH (Boston), production company", 
        "Chedd-Angier Productions, production company", 
        "Film Australia, production company", 
        "John Angier, co-producer", 
        "Andrew Liebman, co-producer", 
        "Andrew Liebman, director"
    ], 
    "colour": [
        "Colour"
    ], 
    "sound_audio": [
        "Sound"
    ], 
    "language_keywords": [
        "English"
    ], 
    "other_languages": [
        ""
    ], 
    "other_language_type": [
        ""
    ], 
    "other_language_notes": [
        ""
    ], 
    "length": [
        "01:00:00"
    ], 
    "audience_classification": [
        "G"
    ], 
    "viewing_guidelines": [
        ""
    ], 
    "form": [
        ""
    ], 
    "genre": [
        "Documentary", 
        "Documentary/Documentary films - Australia"
    ], 
    "subject_group": [
        "Climate, Environment, Natural Resources & Disasters/Air - Pollution", 
        "Climate, Environment, Natural Resources & Disasters/Greenhouse effect, Atmospheric", 
        "Climate, Environment, Natural Resources & Disasters/Ozone layer depletion"
    ], 
    "abstract": [
        ""
    ], 
    "description": [
        "Episode number 2 of Series \"Race to save the planet\". This program examines the new understanding of how human activities are altering the earth's atmosphere. It explores damage to the ozone layer and the greenhouse effect, noting the probable consequences of these changes, and concludes by considering how societies can respond. Teacher's notes accompany the video."
    ], 
    "member_object": [
        ""
    ], 
    "part_of_compliation_title_or_vod_package": [
        ""
    ], 
    "related_objects": [
        "Series; S00982; Race to save the planet; Active; 1990"
    ], 
    "object_relationship": [
        "Series Title"
    ], 
    "related_object_notes": [
        "2"
    ], 
    "active_carriers_public_types_and_formats_only": [
        "VHS; Access Print (Section 1)", 
        "VHS; Access Print (Section 1)"
    ]
}