{
    "system_id": 21722, 
    "permalink": "http://collections.acmi.net.au/objects/21722", 
    "record_type": "Title", 
    "acmi_identifier": "002092", 
    "title": "Circus in Europe", 
    "other_title": [
        ""
    ], 
    "other_title_type": [
        ""
    ], 
    "place_of_production": [
        "Germany"
    ], 
    "creation_date": [
        "1970"
    ], 
    "creator_contributor_role": [
        "Institut f\u00fcr Film und Bild, production company"
    ], 
    "colour": [
        "Colour"
    ], 
    "sound_audio": [
        "Sound"
    ], 
    "language_keywords": [
        "German"
    ], 
    "other_languages": [
        ""
    ], 
    "other_language_type": [
        ""
    ], 
    "other_language_notes": [
        ""
    ], 
    "length": [
        "00:09:00"
    ], 
    "audience_classification": [
        ""
    ], 
    "viewing_guidelines": [
        ""
    ], 
    "form": [
        "Foreign language films", 
        "Short films", 
        "Short films/Short films - Germany"
    ], 
    "genre": [
        "Documentary", 
        "Documentary/Documentary films - Germany"
    ], 
    "subject_group": [
        "Animals & Wildlife/Circus animals", 
        "Anthropology, Ethnology, Exploration & Travel/Travelers", 
        "Music & Performing Arts/Circus animals", 
        "Music & Performing Arts/Circus performers", 
        "Music & Performing Arts/Circus", 
        "Hobbies, Recreation & Sport/Acrobatics"
    ], 
    "abstract": [
        ""
    ], 
    "description": [
        "The arrival of a small circus in a European town, and the parade through the streets. Some of the circus acts are shown, including animal acts and acrobatics. No commentary except for some brief words in German by the circus ringmaster."
    ], 
    "member_object": [
        ""
    ], 
    "part_of_compliation_title_or_vod_package": [
        ""
    ], 
    "related_objects": [
        ""
    ], 
    "object_relationship": [
        ""
    ], 
    "related_object_notes": [
        ""
    ], 
    "active_carriers_public_types_and_formats_only": [
        "16mm film; Access Print (Section 1)"
    ]
}