{
    "system_id": 37888, 
    "permalink": "http://collections.acmi.net.au/objects/37888", 
    "record_type": "Title", 
    "acmi_identifier": "303134", 
    "title": "Counting by 10's and 5's", 
    "other_title": [
        ""
    ], 
    "other_title_type": [
        ""
    ], 
    "place_of_production": [
        "United States"
    ], 
    "creation_date": [
        "1980"
    ], 
    "creator_contributor_role": [
        "Bosustow Entertainment, production company", 
        "Wanda E. Sykes, producer"
    ], 
    "colour": [
        "Colour"
    ], 
    "sound_audio": [
        "Sound"
    ], 
    "language_keywords": [
        "English"
    ], 
    "other_languages": [
        ""
    ], 
    "other_language_type": [
        ""
    ], 
    "other_language_notes": [
        ""
    ], 
    "length": [
        "00:10:00"
    ], 
    "audience_classification": [
        ""
    ], 
    "viewing_guidelines": [
        ""
    ], 
    "form": [
        "Short films", 
        "Short films/Short films - United States"
    ], 
    "genre": [
        "Educational & Instructional", 
        "Childrens Films", 
        "Animation", 
        "Educational & Instructional/Instructional", 
        "Animation/Animated films - United States", 
        "Childrens Films/Children 6-12"
    ], 
    "subject_group": [
        "Mathematics, Science & Technology/Counting"
    ], 
    "abstract": [
        ""
    ], 
    "description": [
        "Episode of Series \"Basic math series\". An animated film which illustrates the pattern inherent in numbers, and outlining the links between counting by fives and counting by tens."
    ], 
    "member_object": [
        ""
    ], 
    "part_of_compliation_title_or_vod_package": [
        ""
    ], 
    "related_objects": [
        "Series; S01021; Basic math series; Active; 1980"
    ], 
    "object_relationship": [
        "Series Title"
    ], 
    "related_object_notes": [
        ""
    ], 
    "active_carriers_public_types_and_formats_only": [
        "VHS; Access Print (Section 1)", 
        "VHS; Access Print (Section 1)", 
        "VHS; Access Print (Section 1)"
    ]
}