{
    "system_id": 24866, 
    "permalink": "http://collections.acmi.net.au/objects/24866", 
    "record_type": "Title", 
    "acmi_identifier": "005670", 
    "title": "Jazzoo", 
    "other_title": [
        ""
    ], 
    "other_title_type": [
        ""
    ], 
    "place_of_production": [
        "United States"
    ], 
    "creation_date": [
        "1967"
    ], 
    "creator_contributor_role": [
        "Tee Pee Productions, production company", 
        "John Camie, director"
    ], 
    "colour": [
        "Colour"
    ], 
    "sound_audio": [
        "Sound"
    ], 
    "language_keywords": [
        ""
    ], 
    "other_languages": [
        ""
    ], 
    "other_language_type": [
        ""
    ], 
    "other_language_notes": [
        ""
    ], 
    "length": [
        "00:18:16"
    ], 
    "audience_classification": [
        ""
    ], 
    "viewing_guidelines": [
        ""
    ], 
    "form": [
        "Short films/Short films - United States", 
        "Short films"
    ], 
    "genre": [
        ""
    ], 
    "subject_group": [
        "Animals & Wildlife/Zoo animals", 
        "Animals & Wildlife/Zoological gardens", 
        "Climate, Environment, Natural Resources & Disasters/Natural history", 
        "Advertising, Film, Journalism, Mass Media & TV/Cinematography", 
        "Music & Performing Arts/Jazz music"
    ], 
    "abstract": [
        ""
    ], 
    "description": [
        "Designed to capture the beauty, colour and activities of a zoo in the early hours of a summer morning, with striking visual images and a lively, original jazz score. Photographed at the St Louis Zoo, we watch the animals commence their day, and their encounters with the early spectators."
    ], 
    "member_object": [
        ""
    ], 
    "part_of_compliation_title_or_vod_package": [
        ""
    ], 
    "related_objects": [
        "Title; 504716; Jazzoo [Short version]; Active; 1969"
    ], 
    "object_relationship": [
        "Related Title"
    ], 
    "related_object_notes": [
        ""
    ], 
    "active_carriers_public_types_and_formats_only": [
        "16mm film; Access Print (Section 1)"
    ]
}