{
    "system_id": 26897, 
    "permalink": "http://collections.acmi.net.au/objects/26897", 
    "record_type": "Title", 
    "acmi_identifier": "007988", 
    "title": "Oscillators", 
    "other_title": [
        ""
    ], 
    "other_title_type": [
        ""
    ], 
    "place_of_production": [
        "United States"
    ], 
    "creation_date": [
        "1944"
    ], 
    "creator_contributor_role": [
        "United States. Navy, production company"
    ], 
    "colour": [
        "Black and White"
    ], 
    "sound_audio": [
        "Sound"
    ], 
    "language_keywords": [
        "English"
    ], 
    "other_languages": [
        ""
    ], 
    "other_language_type": [
        ""
    ], 
    "other_language_notes": [
        ""
    ], 
    "length": [
        "00:13:13"
    ], 
    "audience_classification": [
        ""
    ], 
    "viewing_guidelines": [
        ""
    ], 
    "form": [
        "Short films", 
        "Short films/Short films - United States"
    ], 
    "genre": [
        "Educational & Instructional", 
        "Educational & Instructional/Instructional"
    ], 
    "subject_group": [
        "Advertising, Film, Journalism, Mass Media & TV/Radio frequency", 
        "Mathematics, Science & Technology/Electric circuits", 
        "Mathematics, Science & Technology/Electronics", 
        "Mathematics, Science & Technology/Oscillators, Audio-frequency"
    ], 
    "abstract": [
        ""
    ], 
    "description": [
        "Episode of Series \"Radio Technician Training\". Explains the basic principles of electronic oscillation and variations in oscillations are studied; functioning of a common circuit and tank circuit are explained by means of animation."
    ], 
    "member_object": [
        ""
    ], 
    "part_of_compliation_title_or_vod_package": [
        ""
    ], 
    "related_objects": [
        "Series; S00629; Radio Technician Training; Active"
    ], 
    "object_relationship": [
        "Series Title"
    ], 
    "related_object_notes": [
        ""
    ], 
    "active_carriers_public_types_and_formats_only": [
        "16mm film; Access Print (Section 1)"
    ]
}