{
    "system_id": 12942, 
    "permalink": "http://collections.acmi.net.au/objects/12942", 
    "record_type": "Title", 
    "acmi_identifier": "B1006910", 
    "title": "Dusty hearts", 
    "other_title": [
        ""
    ], 
    "other_title_type": [
        ""
    ], 
    "place_of_production": [
        "Australia"
    ], 
    "creation_date": [
        "1991"
    ], 
    "creator_contributor_role": [
        "Pauline Chan, director", 
        "Mariel Beros, producer", 
        "Geoff Morrell, cast", 
        "Tina Bursill, cast", 
        "AFTRS, production company"
    ], 
    "colour": [
        "Colour"
    ], 
    "sound_audio": [
        "Sound"
    ], 
    "language_keywords": [
        "English"
    ], 
    "other_languages": [
        ""
    ], 
    "other_language_type": [
        ""
    ], 
    "other_language_notes": [
        ""
    ], 
    "length": [
        "00:28:53"
    ], 
    "audience_classification": [
        "Mediatheque - not for children (ACMI classified)"
    ], 
    "viewing_guidelines": [
        "Educational use only", 
        "Coarse language"
    ], 
    "form": [
        "Short films", 
        "Short films/Short films - Australia"
    ], 
    "genre": [
        "Amateur & Student Films", 
        "Amateur & Student Films/Student films - Australia"
    ], 
    "subject_group": [
        "Places/Outback Australia", 
        "Economics, Philosophy, Politics, Religion & Sociology/Reality"
    ], 
    "abstract": [
        "A black comedy about one man's destiny."
    ], 
    "description": [
        "Sax Elthan is a hapless musician, a refugee from the inner city. Rejected by his girlfriend, he travels to the outback to look for work. One burning Wednesday he finds himself beside a highway, waiting for a lift, contemplating his future. It arrives in the shape of a beat-up Volkswagon with a wardrobe tied to the roof. A black comedy about one man's destiny starring Geoff Morrell (Blue Heelers, Changi). Also features Tina Bursill."
    ], 
    "member_object": [
        ""
    ], 
    "part_of_compliation_title_or_vod_package": [
        "Compilation title; B2000583; AFTRS top 100 films. Compile 4; Active; 1973-2004"
    ], 
    "related_objects": [
        "Collection; B2000457; AFTRS top 100 films: 1973-2004; Active; 1973-2004"
    ], 
    "object_relationship": [
        "higher term"
    ], 
    "related_object_notes": [
        ""
    ], 
    "active_carriers_public_types_and_formats_only": [
        "Mediatheque VoD Digital Access Copy"
    ]
}