{
    "system_id": 159667, 
    "permalink": "http://collections.acmi.net.au/objects/159667", 
    "record_type": "VoD Program", 
    "acmi_identifier": "B2002769", 
    "title": "Hollywood Costume: the Interviews", 
    "other_title": [
        ""
    ], 
    "other_title_type": [
        ""
    ], 
    "place_of_production": [
        ""
    ], 
    "creation_date": [
        "2013"
    ], 
    "creator_contributor_role": [
        ""
    ], 
    "colour": [
        ""
    ], 
    "sound_audio": [
        ""
    ], 
    "language_keywords": [
        "English"
    ], 
    "other_languages": [
        ""
    ], 
    "other_language_type": [
        ""
    ], 
    "other_language_notes": [
        ""
    ], 
    "length": [
        "03:04:48"
    ], 
    "audience_classification": [
        ""
    ], 
    "viewing_guidelines": [
        ""
    ], 
    "form": [
        ""
    ], 
    "genre": [
        ""
    ], 
    "subject_group": [
        ""
    ], 
    "abstract": [
        "Hear from the experts about the ACMI 'Hollywood Costume' exhibition."
    ], 
    "description": [
        "These five films take you behind the scenes and allow you to get a deeper insight about what it takes to be a costume designer and put on such a great exhibition. Filmmakers, costume designers and curators are interviewed and the works also include a sneak-peek at some of the wonderful costumes to be discovered in the 'Hollywood Costume' exhibition."
    ], 
    "member_object": [
        "Title; B2002770; Hollywood Costume. Inside the wardrobe: panel discussion; Active; 24 Apr 2013", 
        "Title; B2002768; Hollywood Costume: Deborah Nadoolman Landis interview; Active; 22 Apr 2013", 
        "Title; B2002760; Hollywood Costume: Interview with Jan Chapman and Janet Patterson; Active; 27 Mar 2013", 
        "Title; B2002880; Hollywood Costume: What is Costume Design? with Prof. D. Nadoolman Landis; Active; 24 Apr 2013", 
        "Title; B2002881; In conversation with Chris Dercon and Kaat Debo; Active; 17 Jul 2013"
    ], 
    "part_of_compliation_title_or_vod_package": [
        ""
    ], 
    "related_objects": [
        ""
    ], 
    "object_relationship": [
        ""
    ], 
    "related_object_notes": [
        ""
    ], 
    "active_carriers_public_types_and_formats_only": [
        ""
    ]
}